{
  "الاسم": "AHMAD JABAR",
  "البريد_الالكتروني": "ahmad.jper.aj@gmail.com",
  "الهاتف": "962 6667736",
  "المهارات": [
    "مطور جافا",
    "مطور تطبيقات ويب كامل",
    "Git",
    "GITHUB",
    "القدرة على العمل في فريق",
    "MySQL",
    "Firebase",
    "Dart",
    "Flutter"
  ],
  "الخبرة": "مطور Mendix في شركة Polaris IT من 03/2023 إلى 05/2023.",
  "التعليم": "بكالوريوس في علوم الحاسوب من الجامعة الهاشمية، بمعدل 3.2 من 4.0.",
  "الملخص": "مطور جافا يسعى للعمل في منظمة ذات سمعة طيبة لتوسيع مهاراته. لديه خبرة في تطوير تطبيقات الويب باستخدام Java REST API وJava 2EE.",
  "الثقة": {
    "الاسم": 100,
    "البريد_الالكتروني": 100,
    "الهاتف": 100,
    "المهارات": 100,
    "الخبرة": 100,
    "التعليم": 100
  },
  "is_valid_cv": true,
  "output_language": "ar"
}