{
  "الاسم": "Ahmed Al-Hassan",
  "البريد_الالكتروني": "ahmed.alhassan@email.com",
  "الهاتف": "+962 7XXXXXXX",
  "المهارات": [
    "تطوير تطبيقات الموبايل: Flutter, Dart, بنية تطبيقات الموبايل",
    "تكامل الواجهة الخلفية: RESTful APIs, Firebase",
    "تنفيذ واجهة المستخدم وتجربة المستخدم: التعاون مع المصممين, تصميم المواد",
    "جودة الكود: مراجعات الكود, كود نظيف, أفضل ممارسات الكفاءة",
    "التحكم في الإصدارات: Git, GitHub, GitLab",
    "تحسين الأداء: إدارة الذاكرة, تحسين السرعة, كفاءة التطبيق",
    "الأمان: الامتثال لخصوصية البيانات, التشفير, مكالمات API الآمنة",
    "المنهجية الرشيقة: Scrum, الاجتماعات اليومية, تخطيط السبرينت, المراجعات",
    "الأدوات والمنصات: Android Studio, Xcode, Firebase, Jira, Bitbucket"
  ],
  "الخبرة": "مهندس برمجيات موبايل في شركة الحلول الرقمية، عمان، الأردن من يناير 2022 حتى الآن. تطوير تطبيقات موبايل باستخدام Flutter، تكامل مع RESTful APIs وFirebase، تحسين الأداء، وضمان جودة الكود.",
  "التعليم": "بكالوريوس في علوم الحاسوب من الجامعة الأردنية، عمان، الأردن، تاريخ التخرج: يونيو 2021.",
  "الملخص": "مهندس برمجيات موبايل ذو مهارات عالية ونتائج موجهة مع أكثر من عامين من الخبرة في تطوير وصيانة تطبيقات الموبايل، متخصص في إطار عمل Flutter. يسعى للمساهمة في مبادرات البنك الرقمي المبتكرة.",
  "الثقة": {
    "الاسم": 100,
    "البريد_الالكتروني": 100,
    "الهاتف": 100,
    "المهارات": 100,
    "الخبرة": 100,
    "التعليم": 100
  },
  "is_valid_cv": true,
  "output_language": "ar"
}